collective.blog-1.0.1-py3.8-nspkg.pth
collective/blog/__init__.py
collective/blog/configure.zcml
collective/blog/dependencies.zcml
collective/blog/interfaces.py
collective/blog/permissions.zcml
collective/blog/profiles.zcml
collective/blog/testing.py
collective/blog/utils.py
collective/blog/behaviors/__init__.py
collective/blog/behaviors/blog.py
collective/blog/behaviors/configure.zcml
collective/blog/behaviors/tags.py
collective/blog/content/__init__.py
collective/blog/content/author.py
collective/blog/content/blog.py
collective/blog/content/post.py
collective/blog/content/tag.py
collective/blog/controlpanel/__init__.py
collective/blog/controlpanel/configure.zcml
collective/blog/controlpanel/controlpanel.py
collective/blog/indexers/__init__.py
collective/blog/indexers/author.py
collective/blog/indexers/configure.zcml
collective/blog/indexers/post.py
collective/blog/indexers/tag.py
collective/blog/locales/__init__.py
collective/blog/locales/collective.blog.pot
collective/blog/locales/update.py
collective/blog/locales/de/LC_MESSAGES/collective.blog.po
collective/blog/locales/en/LC_MESSAGES/collective.blog.po
collective/blog/locales/es/LC_MESSAGES/collective.blog.po
collective/blog/locales/pt_BR/LC_MESSAGES/collective.blog.po
collective/blog/profiles/default/browserlayer.xml
collective/blog/profiles/default/catalog.xml
collective/blog/profiles/default/controlpanel.xml
collective/blog/profiles/default/diff_tool.xml
collective/blog/profiles/default/metadata.xml
collective/blog/profiles/default/repositorytool.xml
collective/blog/profiles/default/rolemap.xml
collective/blog/profiles/default/theme.xml
collective/blog/profiles/default/types.xml
collective/blog/profiles/default/registry/Products.CMFPlone.interfaces.controlpanel.INavigationSchema.xml
collective/blog/profiles/default/registry/collective.blog.interfaces.IBlogSettings.xml
collective/blog/profiles/default/registry/plone.app.querystring.interfaces.IQueryField.xml
collective/blog/profiles/default/types/Author.xml
collective.blog-1.0.1.dist-info/LICENSE.GPL
collective.blog-1.0.1.dist-info/LICENSE.md
collective.blog-1.0.1.dist-info/METADATA
collective.blog-1.0.1.dist-info/WHEEL
collective.blog-1.0.1.dist-info/entry_points.txt
collective.blog-1.0.1.dist-info/namespace_packages.txt
collective.blog-1.0.1.dist-info/top_level.txt
collective.blog-1.0.1.dist-info/RECORD
