Metadata-Version: 2.1
Name: collective.blog
Version: 1.0.1
Summary: A Blog-Addon for Plone.
Home-page: https://github.com/collective/collective.blog
Author: Jonas Piterek (kitconcept GmbH)
Author-email: info@kitconcept.com
License: GPL version 2
Project-URL: PyPI, https://pypi.python.org/pypi/collective.blog
Project-URL: Source, https://github.com/collective/collective.blog
Project-URL: Tracker, https://github.com/collective/collective.blog/issues
Keywords: Python Plone CMS
Classifier: Development Status :: 5 - Production/Stable
Classifier: Environment :: Web Environment
Classifier: Framework :: Plone
Classifier: Framework :: Plone :: Addon
Classifier: Framework :: Plone :: Distribution
Classifier: Framework :: Plone :: 6.0
Classifier: Programming Language :: Python
Classifier: Programming Language :: Python :: 3.8
Classifier: Programming Language :: Python :: 3.9
Classifier: Programming Language :: Python :: 3.10
Classifier: Programming Language :: Python :: 3.11
Classifier: Operating System :: OS Independent
Classifier: License :: OSI Approved :: GNU General Public License v2 (GPLv2)
Requires-Python: >=3.8
License-File: LICENSE.GPL
License-File: LICENSE.md
Requires-Dist: setuptools
Requires-Dist: Plone
Requires-Dist: plone.api
Requires-Dist: plone.restapi
Provides-Extra: test
Requires-Dist: zest.releaser[recommended]; extra == "test"
Requires-Dist: zestreleaser.towncrier; extra == "test"
Requires-Dist: plone.app.testing; extra == "test"
Requires-Dist: plone.restapi[test]; extra == "test"
Requires-Dist: pytest; extra == "test"
Requires-Dist: pytest-cov; extra == "test"
Requires-Dist: pytest-plone>=0.2.0; extra == "test"
